[
    {
        "element_id": "24f52c2f91c5c0ac900639105186e328",
        "text": "S. R. P. Silva · R. R. Maciel · M. C. G. Severino",
        "type": "Title",
        "metadata": {
            "source_doc": "s003670050077.pdf",
            "page_number": 1,
            "languages": [
                "eng"
            ],
            "coordinates": [
                23.90399932861328,
                88.50770568847656,
                236.52406311035156,
                98.50770568847656
            ],
            "is_full_width": false
        }
    },
    {
        "element_id": "8d35cddc5731382086a5cd18ee995176",
        "text": "Cenozoic tectonics of Amazon Mouth Basin",
        "type": "Title",
        "metadata": {
            "source_doc": "s003670050077.pdf",
            "page_number": 1,
            "languages": [
                "eng"
            ],
            "coordinates": [
                23.90399932861328,
                107.13722229003906,
                317.8339538574219,
                122.56446838378906
            ],
            "is_full_width": false
        }
    },
    {
        "element_id": "416723103f6cedec232ddcc567ac7b60",
        "text": "Received: 20 August 1996 / Revision received: 11 June 1998",
        "type": "Title",
        "metadata": {
            "source_doc": "s003670050077.pdf",
            "page_number": 1,
            "languages": [
                "eng"
            ],
            "coordinates": [
                23.90399932861328,
                227.09994506835938,
                240.33953857421875,
                235.59994506835938
            ],
            "is_full_width": false
        }
    },
    {
        "element_id": "dbecc952246e27ea84edaf79a31059db",
        "text": "Abstract The Cenozoic shelf margin of the Amazon\nMouth Basin is characterized by a thick prograding prism\nof siliciclastic sediments. This prism, composed mainly of\nUpper Miocene and younger sediments, overlies a Lower\nTertiary\ncarbonate\nshelf.\nTwo\ntectonic—sedimentary\nmodels for the area were developed with the aid of new\ndeep-reﬂection seismic data. Gravitational tectonics dom-\ninate the regional geological framework. Tensional stres-\nses are created near the shelf margin, and compressional\nfeatures dominate at the base of the slope. The morpho-\nlogy of this compressional zone is closely associated with\nthe St. Paul Fracture Zone and the boundary between\ncontinental and oceanic crusts.",
        "type": "NarrativeText",
        "metadata": {
            "source_doc": "s003670050077.pdf",
            "page_number": 1,
            "languages": [
                "eng"
            ],
            "coordinates": [
                23.90399169921875,
                262.8027648925781,
                267.2220153808594,
                410.250732421875
            ],
            "is_full_width": false
        }
    },
    {
        "element_id": "34c2d961af240fb5608aecf3a2047c4d",
        "text": "Introduction",
        "type": "Title",
        "metadata": {
            "source_doc": "s003670050077.pdf",
            "page_number": 1,
            "languages": [
                "eng"
            ],
            "coordinates": [
                23.90399932861328,
                435.9209899902344,
                70.94400024414062,
                445.08612060546875
            ],
            "is_full_width": false
        }
    },
    {
        "element_id": "1dee40df1923f6b89b8c1033dd6ef643",
        "text": "The Amazon Mouth Basin, located on the northwest part\nof the Brazilian equatorial continental margin, covers an\narea of about 360,000 km2 (Fig. 1). This area includes the\ncontinental shelf, slope, and deep basin down to the\n3000-m isobath. The base of the stratigraphic sequence is\ncomposed\nof\nrift\nsediments\nof\nAptian—Albian\nage\n(120 Ma) that are related to the South Atlantic opening\n(Castro et al. 1978; Resende and Ferradaes 1971). There\nare three main drift sequences that overlie the rift\nsediments: an earlier\ntransgressive marine sequence\n(100—65 Ma), a carbonate platform (65—10 Ma), and\na younger, thick prograding siliciclastic marine sequence\n(10—0 Ma) related to\nAmazon River sedimentation.\nThe central part of the Cenozoic shelf margin, known as\n‘‘Cone do Amazonas’’, is aﬀected by intense gravity\ntectonics (Fig. 1).\nA structural analysis of the Amazon mouth basin was\nﬁrst presented by Resende and Ferradaes (1971). In their",
        "type": "NarrativeText",
        "metadata": {
            "source_doc": "s003670050077.pdf",
            "page_number": 1,
            "languages": [
                "eng"
            ],
            "coordinates": [
                23.90399932861328,
                458.4987487792969,
                267.11004638671875,
                663.2587280273438
            ],
            "is_full_width": false
        }
    },
    {
        "element_id": "d6f08a0faa23cb44e4cad0377b75541c",
        "text": "S. R. P. Silva (\n) ) R. R. Maciel ) M. C. G. Severino\nPetrobra´ s, Av. Repu´ blica do Chile, 65/1301E. Centro,\nRio de Janeiro, Brasil, CEP 20035-900",
        "type": "Title",
        "metadata": {
            "source_doc": "s003670050077.pdf",
            "page_number": 1,
            "languages": [
                "eng"
            ],
            "coordinates": [
                23.90399932861328,
                685.422607421875,
                227.54791259765625,
                713.1754150390625
            ],
            "is_full_width": false
        }
    },
    {
        "element_id": "7ec954762ea504c267ba793efadcdc3b",
        "text": "work this area was studied using gravity, magnetic, seis-\nmic, and well-hole data. Later, Castro et al. (1978) investi-\ngated this basin, using more seismic and well data, and\nemphasized the Tertiary stratigraphy and structural\nframework. In this paper we show the results of the struc-\ntural and seismic stratigraphic analysis and the inﬂuence\nof the sedimentation and give a description of the\ntectonic—sedimentary models constructed for all the\nCenozoic sequences, including model developed from\nboth previous and new seismic data.",
        "type": "NarrativeText",
        "metadata": {
            "source_doc": "s003670050077.pdf",
            "page_number": 1,
            "languages": [
                "eng"
            ],
            "coordinates": [
                279.864013671875,
                263.3066711425781,
                523.02392578125,
                376.41064453125
            ],
            "is_full_width": false
        }
    },
    {
        "element_id": "d3c70be9b61caaec0d77ca00b1af37cf",
        "text": "Methodology",
        "type": "Title",
        "metadata": {
            "source_doc": "s003670050077.pdf",
            "page_number": 1,
            "languages": [
                "eng"
            ],
            "coordinates": [
                279.864013671875,
                406.0409851074219,
                329.7840270996094,
                415.20611572265625
            ],
            "is_full_width": false
        }
    },
    {
        "element_id": "c987c8b4c328b390e5f4b5cb34a1ee04",
        "text": "For this work we used multichannel seismic reﬂection\nproﬁles and gravity and well data. The seismic reﬂection\ndata were collected along lines 15,000 km long and spaced\n10—40 km apart. In the Cone do Amazonas region, this\ndata set includes 4500 km of new deep-penetration\nseismic data collected at 12 and 18 s recorded time. The\nprevious seismic data were reprocessed using wavelet de-\nconvolution, multiple attenuation, and after-stack fre-\nquency ﬁlters. Gravity data, collected on a 10]10-km\ngrid, were used to prepare Bouguer and Bouguer-ﬁltered\nmaps and 2D gravity models (Fig. 2); some of these data\nare available in the work presented by Silva and Rodarte\n(1989) and Braga (1991). The integration of these data\nwith the seismic observations allowed us to deﬁne the\ntectonic framework and the boundary between continen-\ntal and oceanic crusts.\nThe interpretation of seismic sections was integrated\nwith data from 26 wells and led to the identiﬁcation of six\nmegasequences: one rift (Early Cretaceous) and ﬁve drift\n(Late Cretaceous and Cenozoic). The drift megasequences\ncomprise the following time intervals: Late Cretaceous\n(100—65 Ma), Paleocene—Eocene (65—40 Ma), Oligocene\n(40—25 Ma), Early to Middle Miocene (25—10 Ma), and\nLate Miocene to Recent (10—0 Ma) (Fig. 3). The limits of\nthese megasequences were mapped and converted to",
        "type": "NarrativeText",
        "metadata": {
            "source_doc": "s003670050077.pdf",
            "page_number": 1,
            "languages": [
                "eng"
            ],
            "coordinates": [
                279.864013671875,
                428.6187438964844,
                523.1539306640625,
                713.5147094726562
            ],
            "is_full_width": false
        }
    },
    {
        "element_id": "60b963f14d3a1ad4c16f99476718ffd7",
        "text": "Fig. 1 Location map of Amazon\nMouth Basin. AA@: Position of\nseismic and geological section.\nThe 3000-m and 200-m\nbathymetric contours are shown.\nThe heavy line is the shelf edge of\nthe Upper Miocene, the\nsouthwestern limit of Cone do\nAmazonas",
        "type": "NarrativeText",
        "metadata": {
            "source_doc": "s003670050077.pdf",
            "page_number": 2,
            "languages": [
                "eng"
            ],
            "coordinates": [
                23.90399932861328,
                55.81198501586914,
                143.40550231933594,
                139.98141479492188
            ],
            "is_full_width": false
        }
    },
    {
        "element_id": "9e1accdb62cefadbb056e68ba7348ec2",
        "text": "Fig. 2 Crustal model AA@,\nlocation shown in Fig. 1. Values\nin parentheses indicate assumed\ndensities",
        "type": "Title",
        "metadata": {
            "source_doc": "s003670050077.pdf",
            "page_number": 2,
            "languages": [
                "eng"
            ],
            "coordinates": [
                23.90399932861328,
                460.9520263671875,
                142.07102966308594,
                498.0390319824219
            ],
            "is_full_width": false
        }
    },
    {
        "element_id": "61e024bec06b8b7e227db46740cfbe0e",
        "text": "Fig. 3 Multichannel seismic section AA@, location shown in Fig. 1,\nillustrating the carbonate platform on the left side between 2 and 4 s,\norigin of growth faults along the shelf margin and thrust faults on\nthe central part. Dashed fault line: fault of St. Paul Fracture Zone",
        "type": "NarrativeText",
        "metadata": {
            "source_doc": "s003670050077.pdf",
            "page_number": 3,
            "languages": [
                "eng"
            ],
            "coordinates": [
                23.90399169921875,
                233.35997009277344,
                266.9275817871094,
                270.4469299316406
            ],
            "is_full_width": false
        }
    },
    {
        "element_id": "46ab55bb6a6c988500d57c6ff80ce1f9",
        "text": "depth (Fig. 4). This allowed us to prepare structural and\nisopach maps for each of the megasequences.",
        "type": "NarrativeText",
        "metadata": {
            "source_doc": "s003670050077.pdf",
            "page_number": 3,
            "languages": [
                "eng"
            ],
            "coordinates": [
                23.90399932861328,
                289.7307434082031,
                266.924072265625,
                311.1787414550781
            ],
            "is_full_width": false
        }
    },
    {
        "element_id": "1c9feeb124d77e12b9da270db4d550d9",
        "text": "Results",
        "type": "Title",
        "metadata": {
            "source_doc": "s003670050077.pdf",
            "page_number": 3,
            "languages": [
                "eng"
            ],
            "coordinates": [
                23.90399932861328,
                336.8489990234375,
                53.18400192260742,
                346.0141296386719
            ],
            "is_full_width": false
        }
    },
    {
        "element_id": "d17eb3437d3cbcc710fe194013f4cd8c",
        "text": "In seismic reﬂection proﬁles, the Paleocene—Middle Miocene\nmegasequence appears as continuous, parallel, high-ampli-\ntude seismic facies (Fig. 3). This pattern indicates a relative-\nly stable platform. Well-hole data also indicate a carbonate\nplatform environment for most of this megasequence. Some\nplatform subenvironments, such as banks of red algae, large\nforaminifera, and ooliths, are described in this area (Wolﬀ\nand Carozzi 1984). The continental shelf at the mouth of\nthe Amazon River is 300 km wide. The megasequences\ninterval thicknesses are 1000 m for Paleocene—Eocene,\n200 m for Oligocene, and 1500 m for Early to Middle\nMiocene. On the Amapa coast (Fig. 5), shelf sediments are\nthinner (1200 m) and the width is narrower (120 km) for the",
        "type": "NarrativeText",
        "metadata": {
            "source_doc": "s003670050077.pdf",
            "page_number": 3,
            "languages": [
                "eng"
            ],
            "coordinates": [
                23.90399932861328,
                359.3534240722656,
                267.01397705078125,
                506.8747253417969
            ],
            "is_full_width": false
        }
    },
    {
        "element_id": "1d08808db81a0501b10c852c321dab15",
        "text": "Fig. 4 Geological section located in the central part of the Cone do\nAmazonas. AA@ refers to the line shown in Fig. 1. Dashed fault line:\nfault of St. Paul Fracture Zone. The ﬁgure shows the two areas of\nextension and compression",
        "type": "NarrativeText",
        "metadata": {
            "source_doc": "s003670050077.pdf",
            "page_number": 3,
            "languages": [
                "eng"
            ],
            "coordinates": [
                23.903995513916016,
                524.3880004882812,
                266.96234130859375,
                561.3272705078125
            ],
            "is_full_width": false
        }
    },
    {
        "element_id": "f6cda2f045310d806922a565bdfcea13",
        "text": "Paleocene—Middle Miocene interval. In the central part of\nthe basin, from the Paleocene to the Middle Miocene, the\nshelf edge deviates from the NW—SE trend seen today.\nThe shelf edge shows a reentrant conﬁguration that marks\nthe southwestern limit of the so-called Cone do Amazonas\n(Fig. 1). Canyons cutting the platform near the shelf edge\nare most common in this area (Fig. 5). In the Cone do\nAmazonas region, the Paleocene—Middle Miocene mega-\nsequences have two depocenters. The southeastern one is\nabout 5500 m thick and the northwestern one is about\n5000 m thick (Fig. 5). Near the shelf edge these sediments\nare deformed by listric faults and by thrust faults farther\nseaward (Fig. 3). In contrast, out of the Cone do Ama-\nzonas region, the deep basin sediments are thinner\n(1000 m, Fig. 5) and less aﬀected by gravity tectonics.\nThe younger Late Miocene—Recent megasequence\nappears in seismic proﬁles with a low-amplitude discon-\ntinuous seismic facies (Fig. 3). This megasequence has a\nprogradational feature. A ﬂuvio deltaic—continental slope\nsystem was determined from sedimentary and petro-\ngraphic studies of well samples (Castro et al. 1978). Well-\nlog analysis indicated overpressured sediments in this\nmegasequence (Franke 1975). During this period of time,\nthe continental shelf edge migrated to form the present-\nday regional NW—SE trend (Fig. 1). In response to the\ngreat increase in the sediment supply rate and associated\ngravity tectonics, the shelf edge shows a slightly convex\neastward shape. This progradational prism is 9000 m",
        "type": "NarrativeText",
        "metadata": {
            "source_doc": "s003670050077.pdf",
            "page_number": 3,
            "languages": [
                "eng"
            ],
            "coordinates": [
                279.864013671875,
                232.34539794921875,
                523.0037841796875,
                551.65869140625
            ],
            "is_full_width": false
        }
    },
    {
        "element_id": "f1067930793d3f47ebeb631f3caca0e4",
        "text": "Fig. 5 Isopach map of\nPaleocene—Middle Miocene\nmegasequence (10—65 Ma).\nContour interval 500 m. The\nheavy line is the shelf edge of the\nPaleocene. C: canyons",
        "type": "NarrativeText",
        "metadata": {
            "source_doc": "s003670050077.pdf",
            "page_number": 4,
            "languages": [
                "eng"
            ],
            "coordinates": [
                23.903995513916016,
                55.81198501586914,
                143.29501342773438,
                111.61441802978516
            ],
            "is_full_width": false
        }
    },
    {
        "element_id": "415c11e74453e34b95208556b7c0fa23",
        "text": "thick at the northwestern part of the Cone do Amazonas\nregion (Figs. 4 and 6). Elsewhere in the basin, it is only\n1200 m thick (Fig. 6).\nThere are several regularly spaced and relatively con-\ntinuous listric faults between the shelf edge and the Late\nMiocene—Recent depocenter. These faults commonly\ntrend along the same fault surfaces as the Paleocene—\nMiddle Miocene early gravity faults (Figs. 3 and 7). In the\ndepocenter there is another set of listric faults, aﬀecting\nonly the Late Miocene—Recent megasequence (Figs. 4 and\n7). In this set, the faults are laterally shorter and farther\napart. On the deeper part of the Cone do Amazonas\nregion, there are two sets of thrust faults associated with\ngravity tectonics (Figs. 4 and 7): a northwestern one and\na southeastern one (near the shelf edge). Their external\nlimits are the transition zone for continental and oceanic\ncrust. The St. Paul Fracture Zone is closely related to\noﬀsets of both features (Fig. 7). The intense sedimentation\nduring the Late Miocene—Recent (related with the Ama-\nzon River) and the associated gravity tectonics led to the\npresent convex surface of the ocean bottom (Fig. 8).",
        "type": "NarrativeText",
        "metadata": {
            "source_doc": "s003670050077.pdf",
            "page_number": 4,
            "languages": [
                "eng"
            ],
            "coordinates": [
                23.90399932861328,
                398.2347717285156,
                267.1450500488281,
                637.3387451171875
            ],
            "is_full_width": false
        }
    },
    {
        "element_id": "4996b8779d1931ed71c5431b257e3429",
        "text": "Discussion",
        "type": "Title",
        "metadata": {
            "source_doc": "s003670050077.pdf",
            "page_number": 4,
            "languages": [
                "eng"
            ],
            "coordinates": [
                23.90399932861328,
                673.448974609375,
                65.66400146484375,
                682.6141357421875
            ],
            "is_full_width": false
        }
    },
    {
        "element_id": "83ec268fd08fbf0da7754301f2e4e9f3",
        "text": "In\nthe\nAmazon\nMouth\nBasin,\ndeposition\nof\nthe\nPaleocene—Middle Miocene megasequences is closely re-",
        "type": "Title",
        "metadata": {
            "source_doc": "s003670050077.pdf",
            "page_number": 4,
            "languages": [
                "eng"
            ],
            "coordinates": [
                23.90399932861328,
                696.0987548828125,
                266.9640808105469,
                717.5467529296875
            ],
            "is_full_width": false
        }
    },
    {
        "element_id": "58a2e8e914734897de62b69dfe36ff4f",
        "text": "lated to the previous tectonic evolution of the rift. For the\nAmapa coast, the existence of deep grabens indicates\nmajor crustal stretching during the rift phase, which pro-\nmoted a high subsequent thermal subsidence (Fig. 1). In\nfront of the present Amazon mouth, the development of\na large stable shelf was a consequence of a thinner and less\nstretched crust. Great canyons were formed near the shelf\nedge during major times of lowstand sea level in the\nEocene, Oligocene, and Miocene (Figs. 5 and 6) (Silva and\nRodarte, 1989). Clastic sediments bypassed the shelf edge\nthrough these canyons and reached the continental slope.\nAn increase of sedimentary weight (related to sedimenta-\ntion rate) in unstable areas, such as along the continental\nslope, creates ideal conditions for the development of\ngravity tectonics. The importance of these tectonics on the\norigin of growth faulting in deltaic areas, such as the US\nGulf Coast Province and the Niger and Mississippi deltas,\nhas been discussed in the literature (Crans et al. 1980;\nWinker 1982; Galloway 1986).\nIn the Amazon Mouth Basin, Castro et al. (1978) identi-\nﬁed growth faults and interpreted compressional features\nas diapiric structures. The acquisition of new seismic re-\nﬂection data and the use of new processing routines,\nhowever, allowed us to identify the former diapirs as\ncompressional structures (folds and thrust faults) and to\ndeﬁne new tectonic models for this area based on gravity\ngliding and spreading (Galloway 1986). In the ﬁrst\nmodel, gravity gliding creates extensional ﬁelds on the",
        "type": "NarrativeText",
        "metadata": {
            "source_doc": "s003670050077.pdf",
            "page_number": 4,
            "languages": [
                "eng"
            ],
            "coordinates": [
                279.864013671875,
                398.2347412109375,
                523.0439453125,
                717.5466918945312
            ],
            "is_full_width": false
        }
    },
    {
        "element_id": "5bd873c1129cdbae8ba2337cfc5ad40d",
        "text": "Fig. 6 Isopach map of Late\nMiocene—Recent megasequence\n(0—10 Ma). C: canyons. Contour\ninterval is 500 m. The heavy line\nis the shelf edge of Upper\nMiocene",
        "type": "NarrativeText",
        "metadata": {
            "source_doc": "s003670050077.pdf",
            "page_number": 5,
            "languages": [
                "eng"
            ],
            "coordinates": [
                23.90399932861328,
                55.81198501586914,
                142.9975128173828,
                111.61441802978516
            ],
            "is_full_width": false
        }
    },
    {
        "element_id": "95a150639538ce4145b8662d6a2202b9",
        "text": "Fig. 7 Fault map of Miocene\nshowing the growth faults near\nthe shelf edge and thrust faults in\na northeastern direction. It shows\nthe E—W faults of St. Paul\nFracture Zone and transition\nzone between continental and\noceanic crusts",
        "type": "NarrativeText",
        "metadata": {
            "source_doc": "s003670050077.pdf",
            "page_number": 5,
            "languages": [
                "eng"
            ],
            "coordinates": [
                23.90399932861328,
                405.8759460449219,
                143.2949981689453,
                480.6139221191406
            ],
            "is_full_width": false
        }
    },
    {
        "element_id": "5e139bfa4c9681219b91d27471582935",
        "text": "Fig. 8 Bathymetric map.\nContour interval is 250 m. This\nﬁgure shows the convex eastward\nsurface of oceanic bottom",
        "type": "Title",
        "metadata": {
            "source_doc": "s003670050077.pdf",
            "page_number": 6,
            "languages": [
                "eng"
            ],
            "coordinates": [
                23.90399932861328,
                55.81198501586914,
                143.2864990234375,
                92.67899322509766
            ],
            "is_full_width": false
        }
    },
    {
        "element_id": "e6b1666ecb3ae6fa4185549a909f9a68",
        "text": "continental slope (Fig. 9A1). As a result, growth faults and\nrollover structures were formed. The faults tend to termin-\nate over mechanical discontinuities near the top of the rift\nand early Paleocene sequences (Fig. 3). Along these dis-\ncontinuities, the potential energy of sliding is enough to\novercome the internal strength of the sediments, allowing\nthe sedimentary blocks to be carried toward deeper\nwaters. In deep water, the topography of the St. Paul\nFracture Zone and the transition zone between the conti-\nnental and oceanic crust resists this down-slope transla-\ntion. Thus, friction increases on the sliding surfaces near\nthe ridge, and compressional stresses are created. In re-\nsponse to these processes, high subsidence rates and thick\nsedimentary deposits are created at the base of continental\nslope. Another increase in the sediment thickness results\nin the deep-water compressive areas due to the stacking of\noverthrusted blocks (Fig. 9A2).\nThe early Tertiary carbonate deposition on the conti-\nnental shelf was interrupted by the change in the direction\nof ﬂow of the Amazon River, from west to east into the\nAtlantic Ocean, due to the Andean Orogeny (Hoorn\n1993). Consequently, since middle Miocene time, a ﬂuvio\ndeltaic—continental slope system has been developing in\nthe Amazon Mouth Basin.\nThe high capacity of sediment transport by the Amazon\nRiver caused an increase in the sedimentation rates.\nDuring the last second-order lowstand of sea level (Late",
        "type": "NarrativeText",
        "metadata": {
            "source_doc": "s003670050077.pdf",
            "page_number": 6,
            "languages": [
                "eng"
            ],
            "coordinates": [
                23.90399932861328,
                409.6827697753906,
                267.0640869140625,
                717.5467529296875
            ],
            "is_full_width": false
        }
    },
    {
        "element_id": "313a56d2fcefafe17b6c529d7b60d067",
        "text": "Miocene to Recent), this sedimentation prograded to near\nthe shelf edge and stayed there longer than during the\nPaleocene—Middle Miocene time. In the Cone do Ama-\nzonas region, the situation of the relative lowstand of sea\nlevel associated with the increase of sediment inﬂux al-\nlowed the accumulation of large volumes of sediment on\nthe continental slope. The earlier gravity tectonics were\nintensiﬁed mainly because of two factors: increased sedi-\nmentary load in an unstable area, and creation of new\ngliding surfaces. These surfaces tend to follow abnormally\nhigh pressure zones that usually occur in areas of high\nsedimentation rates and rapid subsidence (Dailly 1976).\nThe distribution pattern of a thick sedimentary load,\nmainly on the western side of the Cone do Amazonas\nregion, promoted high subsidence rates. The gravitational\ntectonic intensity led to the northward displacement of the\nwestern part of the Paleocene—Middle Miocene structural\nthickening (Figs. 4 and 5). Thus, the northwestern Paleo-\ncene—Middle Miocene structural thickening is closely\nrelated with the post-Miocene compressional region. The\nsoutheastern sedimentary thickening is related to the ex-\ntensional region that was active during its deposition\n(Fig. 5).\nThe action of gravity over a sedimentary stack pro-\nmotes\nits\nextension\ntoward\nthe\ndeep-basin\nlimits\n(Fig. 9B1). This is the another model (gravity spreading)\nto explain the compressional features present in deep",
        "type": "NarrativeText",
        "metadata": {
            "source_doc": "s003670050077.pdf",
            "page_number": 6,
            "languages": [
                "eng"
            ],
            "coordinates": [
                279.864013671875,
                409.6827087402344,
                523.0538940429688,
                717.5466918945312
            ],
            "is_full_width": false
        }
    },
    {
        "element_id": "4850508217f4123f382c9d8d73af4418",
        "text": "Fig. 9 Cenozoic tectonic model\nfor the Amazon Mouth Basin\n(modiﬁed from Galloway 1986).\nA1 and A2 are stages of gravity\ngliding, B1 and B2 are stages of\ngravity spreading",
        "type": "NarrativeText",
        "metadata": {
            "source_doc": "s003670050077.pdf",
            "page_number": 7,
            "languages": [
                "eng"
            ],
            "coordinates": [
                23.90399932861328,
                55.81198501586914,
                140.26901245117188,
                111.61441802978516
            ],
            "is_full_width": false
        }
    },
    {
        "element_id": "0427c3370744c81b295a4245ff2fe87f",
        "text": "water. As with in the gravity gliding model, the topo-\ngraphies related to the St. Paul Fracture Zone and with\nthe transition zone between continental and oceanic crust\ncreate boundaries for this movement. In consequence,\nfolds and thrust faulting occur due to the establishment\nof compressional ﬁelds (Fig. 9B2).",
        "type": "NarrativeText",
        "metadata": {
            "source_doc": "s003670050077.pdf",
            "page_number": 7,
            "languages": [
                "eng"
            ],
            "coordinates": [
                23.90399932861328,
                295.2027587890625,
                267.0740661621094,
                362.4427490234375
            ],
            "is_full_width": false
        }
    },
    {
        "element_id": "b0011e6fd943c7bcd1e83eb5d4e5ff7f",
        "text": "Conclusions",
        "type": "Title",
        "metadata": {
            "source_doc": "s003670050077.pdf",
            "page_number": 7,
            "languages": [
                "eng"
            ],
            "coordinates": [
                23.90399932861328,
                395.09698486328125,
                70.6240005493164,
                404.2621154785156
            ],
            "is_full_width": false
        }
    },
    {
        "element_id": "fa7a3ffa73780be47b646b59fbc132ad",
        "text": "Major conclusions are:",
        "type": "NarrativeText",
        "metadata": {
            "source_doc": "s003670050077.pdf",
            "page_number": 7,
            "languages": [
                "eng"
            ],
            "coordinates": [
                23.90399932861328,
                417.67474365234375,
                122.05400085449219,
                427.67474365234375
            ],
            "is_full_width": false
        }
    },
    {
        "element_id": "41e51af46f3e5b0404ef4e075bfef4ca",
        "text": "1. The Amazon Cenozoic shelf conﬁguration is closely\nrelated to the previous tectonic evolution of the\nrift.\n2. The Amazon Mouth Basin is a good example of\ngravity tectonics in a complex prograding continental\nmargin.\n3. Near the shelf edge, growth faults and rollover struc-\ntures were formed by gravity gliding. Along the\nmargins of the deep basin, the compressional struc-\ntures were formed by both gravity gliding and spread-\ning.\n4. The morphology of the compressional zone is closely\nassociated with topographic irregularities (ridge) of the\nSt. Paul Fracture Zone and the boundary between\ncontinental and oceanic crusts.\n5. The gravity tectonics active since Paleocene were inten-\nsiﬁed after the Middle Miocene due to the high sedi-\nmentation rates of the Amazon River.",
        "type": "NarrativeText",
        "metadata": {
            "source_doc": "s003670050077.pdf",
            "page_number": 7,
            "languages": [
                "eng"
            ],
            "coordinates": [
                23.90399932861328,
                434.0907287597656,
                267.0180969238281,
                638.8507080078125
            ],
            "is_full_width": false
        }
    },
    {
        "element_id": "796cb356a780043374e77446756539bc",
        "text": "Acknowledgments Thanks go to Dr. A. C. M. Castro Jr for critical\nremarks and suggestions that helped to improve the manuscript, and\nPETROBA¨ S S.A. for permission to publish this paper.",
        "type": "NarrativeText",
        "metadata": {
            "source_doc": "s003670050077.pdf",
            "page_number": 7,
            "languages": [
                "eng"
            ],
            "coordinates": [
                23.90399932861328,
                659.8919677734375,
                266.94451904296875,
                687.3274536132812
            ],
            "is_full_width": false
        }
    },
    {
        "element_id": "058b74240ddb46fb91f7275c1b79c271",
        "text": "References",
        "type": "Title",
        "metadata": {
            "source_doc": "s003670050077.pdf",
            "page_number": 7,
            "languages": [
                "eng"
            ],
            "coordinates": [
                279.864013671875,
                304.4490051269531,
                324.0240173339844,
                313.6141357421875
            ],
            "is_full_width": false
        }
    },
    {
        "element_id": "65bb701fab6698668c114fcc17e85e26",
        "text": "Braga LFS (1991) Isostatic evolution and crustal structures of the\nAmazon continental margin determined by admittance analyses\nand inversion of gravity data. Unpublished PhD thesis. Eugene:\nOregon State University, 161 pp\nCastro JC, Miura K, and Braga JAE (1978) Stratigraphic and struc-\ntural framework of the Foz do Amazonas Basin. Houston, Texas:\n10th Annual Oﬀshore Technology Conference, pp. 1843—1847\nCrans W, Mandl G, and Haremboure J (1980) On the theory of\ngrowth faulting: a geomechanical delta model based on gravity\nsliding. Journal of Petroleum Geology 2 : 265—307\nDailly GC (1976) A possible mechanism relating progradation\ngrowth faulting, clay diapirism and overthrusting in a regressive\nsequence of sediments. Canadian Petroleum Geology Bulletin\n24 : 92—116\nFranke MR (1975) Presso8 es de formaia8 o anormalmente altas.\nBoletim Tecnico da PETROBRAS 18(2): 52—66\nGalloway WE (1986) Growth faults and fault-related structures of\nprograding terrigenous clastic continental margins. Gulf Coast\nAssociation of Geological Societies Transactions 36 : 121—128\nHoorn C (1993) Marine incursions and the inﬂuence of Andean\ntectonics on the Miocene depositional history of northwestern\nAmazonia: results of a palynostratigraphic study. Palaeogeogra-\nphy, Palaeoclimatology, Palaeoecology 105 : 267—309\nResende WM and Ferradaes JO (1971) Integraia8 o geologica re-\ngional da bacia sedimentar da Foz do Amazonas. 25° Congresso\nBrasileiro de Geologia 3 : 203—214\nSilva SRP and Rodarte JBM (1989) Bacias da Foz do Amazonas\ne Para Maranha8 o (aguas profundas): uma analise sismoestrati-\ngraﬁca, tectono-sedimentar e\ntermica. Anais I\nCongresso\nSociedade Brasileira de Geoﬁsica 2 : 843—852\nWinker CD (1982) Cenozoic shelf margins, northwestern Gulf of\nMexico. Gulf Coast Association of Geological Societies Transac-\ntions 32 : 427—448\nWolﬀB and Carozzi AV (1984) Microfacies, depositional environ-\nments, and diagenesis of the Amapa carbonates (Paleocene—\nMiddle Miocene), Foz Amazonas Basin, oﬀshore NE Brazil. In:\nPETROBRAS-CENPES-SINTEP (Ed.), Serie Cieˆ ncia-Tecnica-\nPetroleo, Seia8 o Exploraia8 o de Petroleo 13 : 103 pp",
        "type": "NarrativeText",
        "metadata": {
            "source_doc": "s003670050077.pdf",
            "page_number": 7,
            "languages": [
                "eng"
            ],
            "coordinates": [
                279.86376953125,
                328.1879577636719,
                523.049560546875,
                686.8148803710938
            ],
            "is_full_width": false
        }
    }
]